Workbook

Sheet Maandsamenvatting
A1: 2022 | B1: zakelijk | F1: Prive | I1: BALANS 2022 | J1: 44926 | K1: 44561
A2: Maand | B2: Uren gepland | C2: Inkomsten rijschool | D2: Kilometers | E2: Uurtarief | F2: =IF(Prive!B1="","",Prive!B1) -> ELQ hyp rente | G2: =IF(Prive!C1="","",Prive!C1) -> SVB -PGB Ramasray
A3: januari 2022 | B3: 114 | C3: 3705 | D3: 3079 | E3: 32.5 | F3: =IF(Prive!B2="","",Prive!B2) | G3: =IF(Prive!C2="","",Prive!C2) | I3: ACTIVA
A4: februari 2022 | B4: 123 | C4: 3997.5 | D4: 3333 | E4: 32.5 | F4: =IF(Prive!B3="","",Prive!B3) -> 743.75 | G4: =IF(Prive!C3="","",Prive!C3) | I4: VASTE ACTIVA
A5: maart 2022 | B5: 138 | C5: 4485 | D5: 3770 | E5: 32.5 | F5: =IF(Prive!B4="","",Prive!B4) -> 725.9 | G5: =IF(Prive!C4="","",Prive!C4) | I5: Inventaris (incl computer ed) | J5: =K5 -> 350 | K5: 350
A6: april 2022 | B6: 101 | C6: 3282.5 | D6: 2744 | E6: 32.5 | F6: =IF(Prive!B5="","",Prive!B5) -> 743.75 | G6: =IF(Prive!C5="","",Prive!C5) | I6: afschrijvingen | J6: =K6 -> 150 | K6: 150
A7: mei 2022 | B7: 106 | C7: 3445 | D7: 2869 | E7: 32.5 | F7: =IF(Prive!B6="","",Prive!B6) -> 743.75 | G7: =IF(Prive!C6="","",Prive!C6) | I7: boekwaarde | J7: =J5-J6 -> 200 | K7: 200
A8: juni 2022 | B8: 100 | C8: 3250 | D8: 2683 | E8: 32.5 | F8: =IF(Prive!B7="","",Prive!B7) -> 741.77 | G8: =IF(Prive!C7="","",Prive!C7) | J8: =J7 -> 200 | K8: 200
A9: juli 2022 | B9: 112 | C9: 3640 | D9: 2977 | E9: 32.5 | F9: =IF(Prive!B8="","",Prive!B8) -> 747.72 | G9: =IF(Prive!C8="","",Prive!C8) | I9: VLOTTENDE ACTIVA
A10: augustus 2022 | B10: 140 | C10: 4550 | D10: 3769 | E10: 32.5 | F10: =IF(Prive!B9="","",Prive!B9) -> 805.23 | G10: =IF(Prive!C9="","",Prive!C9) | I10: overige vorderingen | J10: =22*E8 -> 715 | K10: 817
A11: september 2022 | B11: 143 | C11: 4647.5 | D11: 3843 | E11: 32.5 | F11: =IF(Prive!B10="","",Prive!B10) -> 866.72 | G11: =IF(Prive!C10="","",Prive!C10) | J11: =J10 -> 715 | K11: 817
A12: oktober 2022 | B12: 137 | C12: 4452.5 | D12: 3683 | E12: 32.5 | F12: =IF(Prive!B11="","",Prive!B11) -> 989.68 | G12: =IF(Prive!C11="","",Prive!C11) | I12: LIQUIDE MIDDELEN
A13: november 2022 | B13: 131 | C13: 4257.5 | D13: 3505 | E13: 32.5 | F13: =IF(Prive!B12="","",Prive!B12) | G13: =IF(Prive!C12="","",Prive!C12) | I13: Kas/bank | J13: =J27-J8-J11-J14 -> 42440.585 | K13: 15641.875
A14: december 2022 | B14: 110 | C14: 3575 | D14: 2959 | E14: 32.5 | F14: =IF(Prive!B13="","",Prive!B13) -> 1049.18 | G14: =IF(Prive!C13="","",Prive!C13) | I14: priveonttrekkingen | J14: -31200 | K14: -8300
J15: =E335 -> 0 | K15: 7341.8748
A16: Totaal | B16: =SUM(B3:B14) -> 1455 | C16: =SUM(C3:C14) -> 47287.5 | D16: =SUM(D3:D14) -> 39214 | E16: 32.5 | F16: =IF(COUNT(F3:F14)=0,"",SUM(F3:F14)) -> 8157.45 | G16: =IF(COUNT(G3:G14)=0,"",SUM(G3:G14)) | I16: TOTAAL | J16: =SUM(J8,J11,J15) -> 915 | K16: 8358.8748
I18: PASSIVA
A19: Winst- en verliestrekening | I19: Eigen vermogen | J19: =K19+$B25+J14 -> 12155.585 | K19: 9467.4548
A20: Inkomsten - Rijschool | B20: =C16 -> 47287.5
A21: Kosten - Rijschool | B21: =Kosten!D68 -> 4019.485 | I21: Langlopende schulden | J21: =K21 -> 0 | K21: 0
A22: Kosten - km | B22: =D16*0.23 -> 9019.22 | I22: Kortlopende schulden | J22: =K22 -> 0 | K22: 0
A23: Kosten - Internet/Mobiel | B23: 306.4
A24: Totale kosten | B24: 13399.37 | I24: Te Betalen Belastingen | J24: =K24 -> 0 | K24: 0
A25: Resultaat | B25: =B20-B24 -> 33888.13 | I25: cumm | J25: =SUM(J21:J24) -> 0 | K25: 0
C26: =B24+B25 -> 47287.5
I27: TOTAAL | J27: =SUM(J19,J21:J25) -> 12155.585 | K27: 9467.4548
A29: Aantal uren moet nog met 300 worden verminderd

Sheet Rittenplanning
A1: Plandatum | B1: Uren gepland | C1: Km per uur | D1: Kilometers | E1: uren/mnd
A2: 44564 | B2: 4 | C2: 26.25 | D2: 105
A3: 44565 | B3: 3 | C3: 25.67 | D3: 77
A4: 44566 | B4: 5 | C4: 28 | D4: 140
A5: 44567 | B5: 5 | C5: 26.8 | D5: 134
A6: 44568 | B6: 3 | C6: 25.67 | D6: 77
A7: 44569 | B7: 5 | C7: 26.4 | D7: 132
A8: 44571 | B8: 5 | C8: 27.8 | D8: 139
A9: 44572 | B9: 6 | C9: 29.17 | D9: 175
A10: 44573 | B10: 3 | C10: 25 | D10: 75
A11: 44574 | B11: 2 | C11: 26.5 | D11: 53
A12: 44575 | B12: 6 | C12: 27.17 | D12: 163
A13: 44576 | B13: 6 | C13: 25.67 | D13: 154
... A25: 44590 | B25: 4 | C25: 28.25 | D25: 113
A26: 44592 | B26: 5 | C26: 25 | D26: 125 | E26: =SUM(B2:B26) -> 114
A27: 44593 | B27: 6 | C27: 26.83 | D27: 161
A28: 44594 | B28: 6 | C28: 27 | D28: 162
A29: 44595 | B29: 5 | C29: 26.2 | D29: 131
A30: 44596 | B30: 2 | C30: 27 | D30: 54
A31: 44597 | B31: 5 | C31: 28.8 | D31: 144
A32: 44599 | B32: 4 | C32: 28.75 | D32: 115
A33: 44600 | B33: 6 | C33: 25.33 | D33: 152
A34: 44601 | B34: 6 | C34: 27.33 | D34: 164
A35: 44602 | B35: 6 | C35: 26.83 | D35: 161
A36: 44603 | B36: 6 | C36: 27.83 | D36: 167
A37: 44604 | B37: 2 | C37: 27.5 | D37: 55
A38: 44606 | B38: 5 | C38: 28 | D38: 140
... A49: 44618 | B49: 6 | C49: 26.83 | D49: 161
A50: 44620 | B50: 4 | C50: 27 | D50: 108 | E50: =SUM(B27:B50) -> 123
A51: 44621 | B51: 6 | C51: 28.33 | D51: 170
A52: 44622 | B52: 5 | C52: 29.4 | D52: 147
A53: 44623 | B53: 5 | C53: 27.4 | D53: 137
A54: 44624 | B54: 4 | C54: 25 | D54: 100
A55: 44625 | B55: 6 | C55: 26.5 | D55: 159
A56: 44627 | B56: 6 | C56: 27.67 | D56: 166
A57: 44628 | B57: 6 | C57: 27.83 | D57: 167
A58: 44629 | B58: 5 | C58: 27.2 | D58: 136
A59: 44630 | B59: 6 | C59: 27 | D59: 162
A60: 44631 | B60: 3 | C60: 29 | D60: 87
A61: 44632 | B61: 5 | C61: 29 | D61: 145
A62: 44634 | B62: 5 | C62: 27.2 | D62: 136
... A76: 44650 | B76: 5 | C76: 27.2 | D76: 136
A77: 44651 | B77: 4 | C77: 26.25 | D77: 105 | E77: =SUM(B51:B77) -> 138
A78: 44652 | B78: 6 | C78: 28.5 | D78: 171
A79: 44653 | B79: 3 | C79: 26.67 | D79: 80
A80: 44655 | B80: 4 | C80: 27.75 | D80: 111
A81: 44656 | B81: 4 | C81: 27.5 | D81: 110
A82: 44657 | B82: 5 | C82: 29.8 | D82: 149
A83: 44658 | B83: 5 | C83: 27.2 | D83: 136
A84: 44659 | B84: 4 | C84: 27.5 | D84: 110
A85: 44660 | B85: 4 | C85: 24.5 | D85: 98
A86: 44662 | B86: 2 | C86: 29.5 | D86: 59
A87: 44663 | B87: 6 | C87: 27.83 | D87: 167
A88: 44664 | B88: 2 | C88: 31 | D88: 62
A89: 44665 | B89: 4 | C89: 27 | D89: 108
... A100: 44680 | B100: 5 | C100: 25.6 | D100: 128
A101: 44681 | B101: 5 | C101: 26 | D101: 130 | E101: =SUM(B78:B101) -> 101
A102: 44683 | B102: 4 | C102: 27.5 | D102: 110
A103: 44684 | B103: 5 | C103: 28.8 | D103: 144
A104: 44685 | B104: 4 | C104: 28.25 | D104: 113
A105: 44686 | B105: 5 | C105: 26.6 | D105: 133
A106: 44687 | B106: 6 | C106: 25.83 | D106: 155
A107: 44688 | B107: 4 | C107: 26.75 | D107: 107
A108: 44690 | B108: 2 | C108: 28 | D108: 56
A109: 44691 | B109: 4 | C109: 26.5 | D109: 106
A110: 44692 | B110: 4 | C110: 27.5 | D110: 110
A111: 44693 | B111: 4 | C111: 27 | D111: 108
A112: 44694 | B112: 5 | C112: 27 | D112: 135
A113: 44695 | B113: 6 | C113: 28.67 | D113: 172
... A125: 44711 | B125: 3 | C125: 26 | D125: 78
A126: 44712 | B126: 3 | C126: 28 | D126: 84 | E126: =SUM(B102:B126) -> 106
A127: 44713 | B127: 6 | C127: 25.83 | D127: 155
A128: 44714 | B128: 6 | C128: 28.67 | D128: 172
A129: 44715 | B129: 5 | C129: 26.2 | D129: 131
A130: 44716 | B130: 5 | C130: 25.4 | D130: 127
A131: 44719 | B131: 4 | C131: 28.25 | D131: 113
A132: 44720 | B132: 1 | C132: 25 | D132: 25
A133: 44721 | B133: 5 | C133: 27.4 | D133: 137
A134: 44722 | B134: 3 | C134: 26.33 | D134: 79
A135: 44723 | B135: 6 | C135: 26.67 | D135: 160
A136: 44725 | B136: 4 | C136: 27.5 | D136: 110
A137: 44726 | B137: 3 | C137: 24.67 | D137: 74
A138: 44727 | B138: 3 | C138: 27.67 | D138: 83
... A150: 44741 | B150: 5 | C150: 28.6 | D150: 143
A151: 44742 | B151: 1 | C151: 26 | D151: 26 | E151: =SUM(B127:B151) -> 100
A152: 44743 | B152: 5 | C152: 26.4 | D152: 132
A153: 44744 | B153: 5 | C153: 27.4 | D153: 137
A154: 44746 | B154: 1 | C154: 26 | D154: 26
A155: 44747 | B155: 2 | C155: 26.5 | D155: 53
A156: 44748 | B156: 4 | C156: 27.5 | D156: 110
A157: 44749 | B157: 6 | C157: 26.83 | D157: 161
A158: 44750 | B158: 6 | C158: 25.5 | D158: 153
A159: 44751 | B159: 2 | C159: 28 | D159: 56
A160: 44753 | B160: 3 | C160: 26 | D160: 78
A161: 44754 | B161: 3 | C161: 26.33 | D161: 79
A162: 44755 | B162: 3 | C162: 27.33 | D162: 82
A163: 44756 | B163: 2 | C163: 24.5 | D163: 49
... A176: 44771 | B176: 6 | C176: 27.17 | D176: 163
A177: 44772 | B177: 4 | C177: 24.5 | D177: 98 | E177: =SUM(B152:B177) -> 112
A178: 44774 | B178: 2 | C178: 24.5 | D178: 49
...

Sheet Transacties
A1: Transactiedatum | B1: Inkomsten rijschool | C1: Uren afgerond | D1: Km per uur | E1: Kilometers | F1: Weken terug
A2: 44567 | B2: 180 | C2: 6 | D2: 26 | E2: 156 | F2: 15
A3: 44571 | B3: 237 | C3: 7 | D3: 27 | E3: 189 | F3: 15
A4: 44578 | B4: 100 | C4: 3 | D4: 28 | E4: 84 | F4: 15
A5: 44579 | B5: 252 | C5: 8 | D5: 29 | E5: 232 | F5: 15
A6: 44585 | B6: 67 | C6: 2 | D6: 30 | E6: 60 | F6: 15
A7: 44587 | B7: 75 | C7: 2 | D7: 31 | E7: 62 | F7: 15
A8: 44589 | B8: 70 | C8: 2 | D8: 23 | E8: 46 | F8: 15
A9: 44592 | B9: 1102 | C9: 34 | D9: 24 | E9: 816 | F9: 20
A10: 44597 | B10: 390 | C10: 12 | D10: 25 | E10: 300 | F10: 15
A11: 44600 | B11: 342 | C11: 11 | D11: 26 | E11: 286 | F11: 15
A12: 44601 | B12: 300 | C12: 9 | D12: 27 | E12: 243 | F12: 15
A13: 44602 | B13: 372 | C13: 11 | D13: 28 | E13: 308 | F13: 15
... A113: 44916 | B113: 245 | C113: 8 | D113: 29 | E113: 232 | F113: 15
A115: Totaal | B115: =SUM(B2:B113) -> 45402.03 | C115: =SUM(C2:C113) -> 1408 | E115: =SUM(E2:E113) -> 37957

Sheet Kosten
A1: Datum | B1: kosten | C1: Omschrijving | D1: decl.knt | E1: decl%
C2: Lesmateriaal | D2: 72 | E2: 1
C3: Kantoor- en administratiekosten | D3: 40 | E3: 1
C4: Kvk | D4: 48 | E4: 1
C5: Reclame en websitekosten | D5: 120 | E5: 1
A6: 44573 | B6: 2.65 | C6: Kosten BasisPakket | D6: =B6*E6 -> 1.325 | E6: 0.5
A7: 44579 | B7: 30.13 | C7: KPN - Mobiel | D7: =B7*E7 -> 30.13 | E7: 1
A8: 44593 | B8: 21.14 | C8: KPN - Mobiel | D8: =B8*E8 -> 21.14 | E8: 1
A9: 44602 | B9: 3.05 | C9: Kosten BasisPakket | D9: =B9*E9 -> 1.525 | E9: 0.5
A10: 44606 | B10: 2.2 | C10: bedrijfsrest 2461 BARENDRECHT | D10: =B10*E10 -> 2.2 | E10: 1
A11: 44623 | B11: 21.14 | C11: KPN - Mobiel | D11: =B11*E11 -> 10.57 | E11: 0.5
A12: 44630 | B12: 3.05 | C12: Kosten BasisPakket | D12: =B12*E12 -> 1.525 | E12: 0.5
A13: 44630 | B13: 393.25 | C13: Rijschool Mado | D13: =B13*E13 -> 393.25 | E13: 1
A14: 44630 | B14: 3.2 | C14: bedrijfsrest 2461 BARENDRECHT | D14: =B14*E14 -> 3.2 | E14: 1
A15: 44636 | B15: 3.2 | C15: bedrijfsrest 2461 BARENDRECHT | D15: =B15*E15 -> 3.2 | E15: 1
A16: 44651 | B16: 2.95 | C16: bedrijfsrest 2461 BARENDRECHT | D16: =B16*E16 -> 2.95 | E16: 1
A17: 44651 | B17: 2.2 | C17: bedrijfsrest 2461 BARENDRECHT | D17: =B17*E17 -> 2.2 | E17: 1
... A67: 44926 | B67: 22.6 | C67: KPN - Mobiel | D67: =B67*E67 -> 11.3 | E67: 0.5
C68: Totaal | D68: =SUM(D2:D67) -> 4019.485

Sheet Prive
A1: 2022 | B1: ELQ hyp rente | C1: SVB -PGB Ramasray
A2: januari
A3: februari | B3: 743.75
A4: maart | B4: 725.9
A5: april | B5: 743.75
A6: mei | B6: 743.75
A7: juni | B7: 741.77
A8: juli | B8: 747.72
A9: augustus | B9: 805.23
A10: september | B10: 866.72
A11: oktober | B11: 989.68
A12: november
A13: december | B13: 1049.18
A14: Totaal | B14: =SUM(B3:B13) -> 8157.45 | C14: =SUM(C3:C13) -> 0
